pulp_smash/__init__.py
pulp_smash/api.py
pulp_smash/cli.py
pulp_smash/config.py
pulp_smash/constants.py
pulp_smash/exceptions.py
pulp_smash/pulp_smash_cli.py
pulp_smash/selectors.py
pulp_smash/utils.py
pulp_smash/pulp2/__init__.py
pulp_smash/pulp2/constants.py
pulp_smash/pulp2/utils.py
pulp_smash/pulp3/__init__.py
pulp_smash/pulp3/constants.py
pulp_smash/pulp3/utils.py
pulp_smash/tests/__init__.py
pulp_smash/tests/pulp2/__init__.py
pulp_smash/tests/pulp2/docker/__init__.py
pulp_smash/tests/pulp2/docker/utils.py
pulp_smash/tests/pulp2/docker/api_v2/__init__.py
pulp_smash/tests/pulp2/docker/api_v2/test_copy.py
pulp_smash/tests/pulp2/docker/api_v2/test_crud.py
pulp_smash/tests/pulp2/docker/api_v2/test_duplicate_uploads.py
pulp_smash/tests/pulp2/docker/api_v2/test_sync.py
pulp_smash/tests/pulp2/docker/api_v2/test_sync_publish.py
pulp_smash/tests/pulp2/docker/api_v2/test_tags.py
pulp_smash/tests/pulp2/docker/api_v2/test_upload.py
pulp_smash/tests/pulp2/docker/api_v2/utils.py
pulp_smash/tests/pulp2/docker/cli/__init__.py
pulp_smash/tests/pulp2/docker/cli/test_crud.py
pulp_smash/tests/pulp2/docker/cli/test_sync_publish.py
pulp_smash/tests/pulp2/docker/cli/utils.py
pulp_smash/tests/pulp2/ostree/__init__.py
pulp_smash/tests/pulp2/ostree/utils.py
pulp_smash/tests/pulp2/ostree/api_v2/__init__.py
pulp_smash/tests/pulp2/ostree/api_v2/test_copy.py
pulp_smash/tests/pulp2/ostree/api_v2/test_crud.py
pulp_smash/tests/pulp2/ostree/api_v2/test_publish.py
pulp_smash/tests/pulp2/ostree/api_v2/test_sync.py
pulp_smash/tests/pulp2/platform/__init__.py
pulp_smash/tests/pulp2/platform/utils.py
pulp_smash/tests/pulp2/platform/api_v2/__init__.py
pulp_smash/tests/pulp2/platform/api_v2/test_consumer.py
pulp_smash/tests/pulp2/platform/api_v2/test_content_applicability.py
pulp_smash/tests/pulp2/platform/api_v2/test_login.py
pulp_smash/tests/pulp2/platform/api_v2/test_repository.py
pulp_smash/tests/pulp2/platform/api_v2/test_search.py
pulp_smash-2018.7.19.dist-info/METADATA
pulp_smash-2018.7.19.dist-info/RECORD
pulp_smash-2018.7.19.dist-info/WHEEL
pulp_smash-2018.7.19.dist-info/entry_points.txt
pulp_smash-2018.7.19.dist-info/top_level.txt
