Metadata-Version: 2.1
Name: pulp-smash
Version: 2018.7.19
Summary: A library for testing Pulp
Home-page: https://github.com/PulpQE/pulp-smash
Author: Jeremy Audet
Author-email: ichimonji10@gmail.com
License: GPLv3
Platform: UNKNOWN
Classifier: Development Status :: 5 - Production/Stable
Classifier: Intended Audience :: Developers
Classifier: License :: OSI Approved :: GNU General Public License v3 or later (GPLv3+)
Classifier: Programming Language :: Python :: 3.4
Classifier: Programming Language :: Python :: 3.5
Classifier: Programming Language :: Python :: 3.6
Provides-Extra: dev
Requires-Dist: click
Requires-Dist: jsonschema
Requires-Dist: packaging
Requires-Dist: plumbum
Requires-Dist: python-dateutil
Requires-Dist: pyxdg
Requires-Dist: requests
Provides-Extra: dev
Requires-Dist: flake8; extra == 'dev'
Requires-Dist: flake8-docstrings; extra == 'dev'
Requires-Dist: flake8-quotes; extra == 'dev'
Requires-Dist: pydocstyle; extra == 'dev'
Requires-Dist: pylint; extra == 'dev'
Requires-Dist: coveralls; extra == 'dev'
Requires-Dist: sphinx; extra == 'dev'
Requires-Dist: wheel; extra == 'dev'
Requires-Dist: twine; extra == 'dev'
